Metadata-Version: 2.4
Name: astrio-atlas
Version: 0.3.5
Summary: Atlas: Legacy to Modern code modernization
Author-email: Astrio AI <naingoolwin.astrio@gmail.com>
License: Apache-2.0
Keywords: cobol,python,modernization,transpilation,agents
Classifier: Development Status :: 3 - Alpha
Classifier: Intended Audience :: Developers
Classifier: License :: OSI Approved :: Apache Software License
Classifier: Programming Language :: Python :: 3
Classifier: Programming Language :: Python :: 3.14
Requires-Python: >=3.14
License-File: LICENSE
Requires-Dist: litellm>=1.75.0
Requires-Dist: gitpython>=3.1.0
Requires-Dist: diskcache>=5.6.0
Requires-Dist: grep-ast>=0.9.0
Requires-Dist: pathspec>=0.12.0
Requires-Dist: prompt-toolkit>=3.0.0
Requires-Dist: rich>=14.0.0
Requires-Dist: watchfiles>=1.0.0
Requires-Dist: pydantic>=2.0.0
Requires-Dist: python-dotenv>=1.0.0
Requires-Dist: importlib-resources>=6.0.0
Requires-Dist: json5>=0.12.0
Requires-Dist: shtab>=1.7.0
Requires-Dist: configargparse>=1.7.0
Requires-Dist: diff-match-patch>=20241021
Requires-Dist: beautifulsoup4>=4.13.0
Requires-Dist: pyyaml>=6.0.0
Requires-Dist: psutil>=7.0.0
Requires-Dist: pexpect>=4.9.0
Requires-Dist: pillow>=11.0.0
Requires-Dist: pypandoc>=1.15
Requires-Dist: pyperclip>=1.9.0
Requires-Dist: networkx>=3.4.0
Requires-Dist: scipy>=1.15.0
Requires-Dist: socksio>=1.0.0
Requires-Dist: tqdm>=4.67.0
Requires-Dist: pygments>=2.19.0
Requires-Dist: urllib3>=2.6.3
Requires-Dist: aiohttp>=3.13.3
Requires-Dist: markdown-it-py>=4.0.0
Requires-Dist: packaging>=25.0
Requires-Dist: backoff>=2.2.0
Requires-Dist: posthog>=6.5.0
Requires-Dist: mixpanel>=4.10.0
Requires-Dist: oslex>=0.1.3
Provides-Extra: dev
Requires-Dist: pytest>=7.0.0; extra == "dev"
Requires-Dist: pytest-asyncio>=0.21.0; extra == "dev"
Requires-Dist: pytest-cov>=4.0.0; extra == "dev"
Requires-Dist: black>=23.0.0; extra == "dev"
Requires-Dist: ruff>=0.1.0; extra == "dev"
Requires-Dist: mypy>=1.0.0; extra == "dev"
Provides-Extra: playwright
Requires-Dist: playwright>=1.40.0; extra == "playwright"
Dynamic: license-file
